odoo/addons/product_gs1_barcode/README.rst
odoo/addons/product_gs1_barcode/__init__.py
odoo/addons/product_gs1_barcode/__manifest__.py
odoo/addons/product_gs1_barcode/i18n/it.po
odoo/addons/product_gs1_barcode/i18n/product_gs1_barcode.pot
odoo/addons/product_gs1_barcode/models/__init__.py
odoo/addons/product_gs1_barcode/models/gs1_encode_barcode.py
odoo/addons/product_gs1_barcode/readme/CONTRIBUTORS.rst
odoo/addons/product_gs1_barcode/readme/DESCRIPTION.rst
odoo/addons/product_gs1_barcode/readme/USAGE.rst
odoo/addons/product_gs1_barcode/static/description/icon.png
odoo/addons/product_gs1_barcode/static/description/index.html
odoo/addons/product_gs1_barcode/tests/__init__.py
odoo/addons/product_gs1_barcode/tests/test_stock_barcodes_gs1.py
odoo14_addon_product_gs1_barcode-14.0.1.0.1.dev7.dist-info/METADATA
odoo14_addon_product_gs1_barcode-14.0.1.0.1.dev7.dist-info/WHEEL
odoo14_addon_product_gs1_barcode-14.0.1.0.1.dev7.dist-info/top_level.txt
odoo14_addon_product_gs1_barcode-14.0.1.0.1.dev7.dist-info/RECORD
