Metadata-Version: 2.1
Name: odoo14-addon-product_gs1_barcode
Version: 14.0.1.0.1.dev7
Summary: Encoding for GS1-128 (aka UCC/EAN-128) and GS1-Datamatrix
Home-page: https://github.com/OCA/stock-logistics-barcode
Author: Odoo Community Association (OCA), CreuBlanca
Author-email: support@odoo-community.org
License: AGPL-3
Classifier: Programming Language :: Python
Classifier: Framework :: Odoo
Classifier: Framework :: Odoo :: 14.0
Classifier: License :: OSI Approved :: GNU Affero General Public License v3
Requires-Python: >=3.6
Requires-Dist: odoo14-addon-base-gs1-barcode
Requires-Dist: odoo<14.1dev,>=14.0a
